<xml xmlns="http://www.w3.org/1999/xhtml"><block type="onfirstboot" id="onfirstboot" x="75" y="43"><next><block type="sethostname" id="fOf|Zdq}Y_P^k=c!KJ,O"><field name="1">skittlebot</field><next><block type="changesshkeys" id="AqkD1UFLQJsON.nkb^T%"><next><block type="wifisetup" id="yJmP2Kww!hvYM]gPjR!F"><field name="1">yournetwork</field><field name="2">yourpass</field><field name="3">WPA/WPA2</field><next><block type="packageinstall" id="H_JW;9xip^23ML0~1xrP"><field name="1">python-numpy</field><next><block type="packageinstall" id="oiHQu*^am;]lnLwgo5#l"><field name="1">python-opencv</field><next><block type="packageinstall" id="-xRS+xRPWLPTl:N?+*S("><field name="1">python-smbus</field><next><block type="packageinstall" id="8LSWW0gdu#V~gc|N`VEy"><field name="1">python-dev</field><next><block type="changepass" id="!b]_gL5Hoq[RK}3HDG??"><field name="1">skittlebot</field><next><block type="seti2c" id="``l#L=+CgN#Rgi3U!?ki"><field name="1">Enable</field><next><block type="vncenable" id="9[oEE{Vpji}H]!=7Y1TZ"><field name="1">Enable</field><next><block type="runcommand" id="(4Si}2d21PUejNrAx/Qs"><field name="1">git clone https://github.com/orionrobots/skittlebot.git</field><field name="2">pi</field><next><block type="runcommand" id="UV!Nhlpg({VZ~.!6ohz="><field name="1">pip install --user picamera</field><field name="2">pi</field><next><block type="runcommand" id="u;Eq?Bo(+gc4M3}AtuG9"><field name="1">bash /home/pi/skittlebot/install_camera.sh</field><field name="2">root</field><next><block type="downloadfile" id="6UtJy(q;SGKkmwRC30Fn"><field name="1">wget http://4tronix.co.uk/piconz.sh -O piconz.sh</field><field name="2">/home/pi/piconz.sh</field><next><block type="runcommand" id="gT6Br1cYWGZp4ynW5Ca4"><field name="1">bash piconz.sh</field><field name="2">pi</field><next><block type="reboot" id="u(=gp//Q]TT^u=[/{3wv"></block></next></block></next></block></next></block></next></block></next></block></next></block></next></block></next></block></next></block></next></block></next></block></next></block></next></block></next></block></next></block></next></block></xml>